setup.py
collections/defaultdict.py
micropython_collections.defaultdict.egg-info/PKG-INFO
micropython_collections.defaultdict.egg-info/SOURCES.txt
micropython_collections.defaultdict.egg-info/dependency_links.txt
micropython_collections.defaultdict.egg-info/top_level.txt