Metadata-Version: 1.0
Name: micropython-collections.defaultdict
Version: 0.2.1
Summary: collections.defaultdict module for MicroPython
Home-page: https://github.com/micropython/micropython/issues/405
Author: MicroPython Developers
Author-email: micro-python@googlegroups.com
License: MIT
Platform: UNKNOWN
